panda_patrol/__init__.py
panda_patrol/__main__.py
panda_patrol/constants.py
panda_patrol/ai/__init__.py
panda_patrol/ai/generate_data_tests.py
panda_patrol/anomaly_detection/__init__.py
panda_patrol/anomaly_detection/basic_anomaly_detection.py
panda_patrol/backend/__init__.py
panda_patrol/backend/app.py
panda_patrol/backend/models.py
panda_patrol/backend/database/__init__.py
panda_patrol/backend/database/models.py
panda_patrol/backend/static/.DS_Store
panda_patrol/backend/static/asset-manifest.json
panda_patrol/backend/static/config.json
panda_patrol/backend/static/favicon.ico
panda_patrol/backend/static/index.html
panda_patrol/backend/static/logo192.png
panda_patrol/backend/static/logo512.png
panda_patrol/backend/static/robots.txt
panda_patrol/backend/static/css/main.d1be2ffa.css
panda_patrol/backend/static/css/main.d1be2ffa.css.map
panda_patrol/backend/static/js/496.98c5a49f.chunk.js
panda_patrol/backend/static/js/496.98c5a49f.chunk.js.map
panda_patrol/backend/static/js/main.ba9310c0.js
panda_patrol/backend/static/js/main.ba9310c0.js.LICENSE.txt
panda_patrol/backend/static/js/main.ba9310c0.js.map
panda_patrol/backend/utils/__init__.py
panda_patrol/backend/utils/email_utils.py
panda_patrol/backend/utils/slack_utils.py
panda_patrol/checks/__init__.py
panda_patrol/checks/accuracy.py
panda_patrol/checks/check.py
panda_patrol/checks/completeness.py
panda_patrol/checks/constants.py
panda_patrol/checks/duplicate.py
panda_patrol/checks/enums.py
panda_patrol/checks/freshness.py
panda_patrol/checks/utils.py
panda_patrol/checks/volume.py
panda_patrol/data/patrol_result.py
panda_patrol/dbt/__main__.py
panda_patrol/dbt/dbt_to_panda_patrol.py
panda_patrol/dbt/find_dbt_target_results.py
panda_patrol/dbt/main.py
panda_patrol/dbt/run_dbt.py
panda_patrol/headers/__init__.py
panda_patrol/headers/get_headers.py
panda_patrol/parameters/__init__.py
panda_patrol/parameters/adjustable_parameter.py
panda_patrol/parameters/static_parameter.py
panda_patrol/parameters/utils/get_parameter.py
panda_patrol-0.0.102.dist-info/LICENSE
panda_patrol-0.0.102.dist-info/METADATA
panda_patrol-0.0.102.dist-info/WHEEL
panda_patrol-0.0.102.dist-info/top_level.txt
panda_patrol-0.0.102.dist-info/RECORD
