Metadata-Version: 2.1
Name: panda-patrol
Version: 0.0.102
Summary: 🐼 Patrol your data tests
Author-email: Ivan Zhang <ivanzhangofficial@gmail.com>
License: MIT License
Project-URL: Homepage, https://github.com/aivanzhang/panda-patrol
Project-URL: Bug Tracker, https://github.com/aivanzhang/panda-patrol/issues
Requires-Python: >=3.8
License-File: LICENSE
Requires-Dist: fastapi
Requires-Dist: sqlalchemy
Requires-Dist: requests
Requires-Dist: uvicorn[standard]
Requires-Dist: python-dotenv
Requires-Dist: slack-sdk
Requires-Dist: pyod
Requires-Dist: ydata-profiling
Requires-Dist: pandas
